vk7/__init__.py
vk7/admin_tools.py
vk7/streaming_api.py
vk7/utils.py
vk7/vk.py
vk7/vk_api.py
vk7-0.6.dist-info/LICENSE
vk7-0.6.dist-info/METADATA
vk7-0.6.dist-info/WHEEL
vk7-0.6.dist-info/top_level.txt
vk7-0.6.dist-info/RECORD
