Metadata-Version: 2.1
Name: vk7
Version: 0.6
Summary: Framework for extract data from vk.com (russian social network).
Home-page: https://github.com/pash4paul/vk7
Author: Pavel Fomin
Author-email: pash4paul@gmail.com
License: UNKNOWN
Keywords: api data osint social vk.com
Platform: UNKNOWN
Classifier: Development Status :: 3 - Alpha
Classifier: Environment :: Console
Classifier: Intended Audience :: Developers
Classifier: Intended Audience :: Science/Research
Classifier: License :: OSI Approved :: MIT License
Classifier: Programming Language :: Python :: 3
Classifier: Programming Language :: Python :: 3.4
Classifier: Programming Language :: Python :: 3.5
Classifier: Programming Language :: Python :: 3.6
Classifier: Topic :: Software Development :: Libraries :: Python Modules
Requires-Dist: requests (==2.18.4)
